tensordlx/__init__.py
tensordlx/regression.py
tensordlx-0.3.dist-info/METADATA
tensordlx-0.3.dist-info/WHEEL
tensordlx-0.3.dist-info/top_level.txt
tensordlx-0.3.dist-info/RECORD
