Metadata-Version: 2.1
Name: tensordlx
Version: 0.3
Summary: DLcodex
Author: BabaTunde
Classifier: Programming Language :: Python :: 3
